[三元表达式](http://www.coolpython.net/python_senior/senior_feature/three_ternary_expression.html)

[封包与解包](http://www.coolpython.net/python_senior/senior_feature/pack_unpack.html)

[一切皆对象](http://www.coolpython.net/python_senior/senior_feature/everything_is_object.html)

[callable](http://www.coolpython.net/python_senior/senior_feature/callable.html)

[with 语句](http://www.coolpython.net/python_senior/senior_feature/with.html)

[生成式](http://www.coolpython.net/python_senior/senior_feature/comprehensions.html)

[生成器](http://www.coolpython.net/python_senior/senior_feature/generator.html)

[三个实例带你了解生成器的作用](http://www.coolpython.net/python_senior/senior_feature/generator_eg.html)

[迭代器](http://www.coolpython.net/python_senior/senior_feature/iterator.html)

[自省](http://www.coolpython.net/python_senior/senior_feature/introspection.html)

---

# 一切皆对象

1 类就好比模板对象都是根据这个模板刻画衍生出来的



虽然各类教程，包括python官方文档里将int()称之为内置函数，但你查看源码可以发现，它其实是类

- 平时在程序里的各种整型数据，都是这个类生成的
- 这个类是python提供给我们的，而且我们不用关心对象的创建过程。

```python
class int(object):
    """
    int(x=0) -> integer
    int(x, base=10) -> integer
    """
    
    
a = int('3')
print(a, type(a))	#3  <class 'int'>
```



2 类也是对象

用type函数寻找类的“爸爸”/type

- mc的爸爸是MyClass
- MyClass的爸爸是type
- type的爸爸是它自己

```python
class MyClass:
    def print(self):
        print("自己创建的类")


mc = MyClass()
print(mc)			#mc是一个对象 <__main__.MyClass object at 0x101f59828> 

father = type(mc)
print(father)		#是一个类 <class '__main__.MyClass'>

grandfather = type(father)
print(grandfather)	#<class 'type'>

print(type(grandfather))	#<class 'type'>
```



type也是一个类：不管是什么对象，只要你用type去追踪寻找它的爸爸，最终的线索都指向type

- type是个万能的类啊，就连type自己都是对象,所以才有python一切皆对象。

```python
class type(object):
    """
    type(object_or_name, bases, dict)
    type(object) -> the object's type
    type(name, bases, dict) -> a new type
    """
```





类的类型就叫做元类（metaclass）

- 普通的类，可以生成对象，对象也可以称之为实例
- 元类是类，当然也可以生成对象，元类生成的对象就是我们创建的普通类



## 类的创建

类的创建包含下列过程：

1. 遇到class 关键字时，要解析对类的定义，如果没有指定metaclass，那么metaclass 就==默认使用type==
2. 准备namespace，如果元类实现了 `__prepare__` 函数，则会调用它来得到默认的 namespace, 如果没有实现，创建一个空的有序字典作为namespace
3. 调用exec，来执行类的body，类的属性和方法最终都会保存到namespace中
4. 调用类的构造函数来创建类

知道了类的创建过程，知道了元类控制着类的创建，也知道了==默认情况下元类是type==且这个元类是可以设置的，那么如果你想==对类的创建过程进行控制==，进行有目的的定制操作，就可以通过元类来进行



### 直接定义

```python
class MyTest:
    def __init__(self, name):
        self.name = name


mt = MyTest('mytest')
print(mt.name)
```



### 使用type创建

```python
type(name, bases, dict)
'''
name 是类的名字
bases 是继承的类
dict 存放类的属性和方法
'''

	
### 用type来创建一个类，和上面定义的MyTest一模一样的类
def init(self, name):
    self.name = name


mytest_class = type('MyTest', (), {'__init__': init})	#type是类MyTest 的元类
mt = mytest_class('mytest')
print(mt.name)	#mytest
```



# 概念|callable

一个可callable的对象是指==可以被调用执行的对象==：并且可以传入参数

- 另一个简单的描述方式，只要可以在一个对象的后面使用小括号来执行代码，那么这个对象就是callable对象

callable对象的种类：

- 函数
- 类
- 类里的函数
- 实现了`__call__`方法的实例对象



1 函数

函数是python里的一等公民

```python
def test():
    print('ok')

print(callable(test))   # True
test()  # ok
```



2 类

在其他编程语言里，类与函数可以说是两个完全不搭的东西，但在python里，都是可调用对象

```python
class Stu(object):
    def __init__(self, name):
        self.name = name

print(callable(Stu))     # True
print(Stu('小明').name)   # 小明
```



3 类里的方法

本质上也是函数

- 使用isfunction函数可以判断一个对象是否是函数

```python
from inspect import isfunction, ismethod


class Stu(object):
    def __init__(self, name):
        self.name = name

    def run(self):
        print('{name} is running'.format(name=self.name))

print(isfunction(Stu.run))     # True
stu = Stu("小明")
stu.run()        # 小明 is running
```



4 实现了`__call__`方法的实例对象

```python
class Stu(object):

    def __init__(self, name):
        self.name = name

    def __call__(self, *args, **kwargs):
        self.run()

    def run(self):
        print('{name} is running'.format(name=self.name))

stu = Stu('小明')
print(callable(stu))    # True
stu()                   # 小明 is running
```

当你执行stu()时，与调用一个函数有着完全一致的体验，如果不告诉你stu是一个类的实例对象，你还以为stu就是一个函数



# with语句

python中with 语句作为try/finally 编码范式的一种替代, 适用于对资源进行访问的场合，确保不管使用过程中是否发生异常都会执行必要的”清理”操作，释放资源：

- 比如文件使用后自动关闭
- 线程中锁的自动获取和释放等



# 使用with打开文件

```python
with open('data', 'r', encoding='utf-8') as f:
    data = f.readlines()
    
    
### 等价：
f = open('data', 'r', encoding='utf-8')
try:
    data = f.readlines()
except:
    pass
finally:
    f.close()
```



同时打开多个文件：这样做可以减少代码的缩进

```python
with open('a1', 'w')as f1, open('a2', 'w')as f2:
    f1.write('a')
    f2.write('b')
```





## 上下文管理器

概念|上下文管理协议：简单来说，就是实现两个方法，`__enter__()` 和`__exit__()`

实现了`__enter__()` 和`__exit__()`就是上下文管理器

- 由上下文管理器创建，在with语句体代码执行前，通过`__enter__()`进入
- 语句体代码执行结束后，通过`__exit__()`退出



概念|上下文表达式：在with关键字后面的表达式，表达式==返回上下文管理器对象==

概念|语句体：with语句包裹起来的代码



@自定义上下文管理器：可以统计代码段运行时长的上下文管理器

在调试程序性能时，如果只是想知道==某个函数的执行时长==，可以使用一个可以统计函数运行时长的装饰器进行处理，但程序往往很复杂，一段代码里，要做很多操作，不只是调用了一个函数，也可能存在循环，因此，单纯的知道某个函数的执行时长，不能帮助我们更好的了解程序的性能。

需要针对某个代码段进行时间统计，知道这一段代码的执行时长对我们很有帮助

- 可以使用time.time()方法在代码段开始时获取到时间，在结束时再次获取到时间，两个时间做差就可以得到这个代码段的运行时长 => 这种操作方式写起来很麻烦，如果有多处代码段需要统计，就得写多次，很不方便

```python
import time


class ProTime(object):
    def __init__(self, tag=''):
        self.tag = tag

    def __enter__(self):
        self.start_time = time.time()

    def __exit__(self, exc_type, exc_val, exc_tb):
        self.end_time = time.time()
        time_diff = self.end_time - self.start_time
        msg = "代码段{tag}运行时长{time_diff}".format(tag=self.tag, time_diff=time_diff)
        print(msg)


with ProTime('first') as pt:
    # 这里是你要统计运行时长的代码块
    time.sleep(1)

with ProTime('second') as pt:
    # 这里是你要统计运行时长的代码块
    time.sleep(2)
```

关键之处：

- 在with语句所包裹的语句体执行之前，先要执行`__enter__`方法
- 语句体执行结束之后，不论是否有异常，都要执行`__exit__`

在`__exit__`方法里，三个参数提供了异常的全部信息，==如果你想处理异常，可以在这个方法里做处理==。





`__init__` 方法有一个tag参数，设置这个参数的目的，是为了在输出信息里区分多个代码块，如果不想设置这个tag，可以考虑对这个上下文管理器进行修改，通过调用栈获得调用信息，准确的指出是哪个代码段的执行时长

修改后的上下文管理器如下：

```python
import time
import sys


class ProTime(object):
    def __init__(self, tag=''):
        frame = sys._getframe()
        tag_frame = frame.f_back
        self.lineno = tag_frame.f_lineno
        self.filename = tag_frame.f_code.co_filename
        self.tag = tag

    def __enter__(self):
        self.start_time = time.time()

    def __exit__(self, exc_type, exc_val, exc_tb):
        self.end_time = time.time()
        time_diff = self.end_time - self.start_time
        if self.tag:
            msg = "代码段{tag}运行时长{time_diff}".format(tag=self.tag, time_diff=time_diff)
        else:
            msg = "文件{filename} 第 {lineno} 行代码块执行时长{time_diff}".format(filename=self.filename, lineno=self.lineno, time_diff=time_diff)
        print(msg)


with ProTime('first') as pt:
    # 这里是你要统计运行时长的代码块
    time.sleep(1)

with ProTime() as pt:
    # 这里是你要统计运行时长的代码块
    time.sleep(2)


def test():
    with ProTime() as pt:
        # 这里是你要统计运行时长的代码块
        time.sleep(1)

test()
'''output
代码段first运行时长1.0001983642578125
文件<ipython-input-382-7f2b65ff64db> 第 29 行代码块执行时长2.0009377002716064
文件<ipython-input-382-7f2b65ff64db> 第 32 行代码块执行时长1.0003480911254883
'''
```





## 使用with语句控制线程锁的释放

使用with不仅能够自动的关闭打开的文件对象，还可以自动的释放线程锁，这样可以避免死锁的发生

- 为避免多个线程同时对一个变量对象进行修改，在关键语句上加了线程锁

```python
def worker():
    time.sleep(1)
    global a
    for i in range(100000):
        m_lock.acquire()    # 加锁
        a += 1
        m_lock.release()    # 释放锁
```

如果你忘记了写m_lock.release() 对锁进行释放，那么这将导致其他线程永远也无法获取到线程锁 => 这样就形成了死锁

- 上面的代码在acquire之后，使用release释放

```python
def worker():
    time.sleep(1)
    global a
    for i in range(100000):
        with m_lock:	#使用with语句，可以更加优雅地实现加锁和释放锁的操作
            a += 1
```







# 三元表达式

python中并没有三元表达式，但可以通过if语句配合else来实现

java语言中：

```java
int a = 1;
String b = "";
b =  a > 1? "expressionA":"expressionB"	//a > 1这个表达式结果为真时，将"expressionA"赋值给b，反之将"expressionB"赋值给b
System.out.println(b)
```



Python：

```python
a = 1
b = 'expressionA' if a > 1 else 'expressionB'	#当表达式 a > 1 结果为True时，将'expressionA'赋值给b
print(b)
```





# 封包与解包

## 封包

实践中，很少主动使用封包操作



1 将多个值赋值给一个变量时，python会自动将这些值封装成元组

```python
a = 1, 2, 3
print(a, type(a))  # (1, 2, 3) <class 'tuple'>
```



2 当函数返回多个数值时，也会进行封包

```python
def test():
    return 1, 2, 3

a = test()
print(a, type(a))  # (1, 2, 3) <class 'tuple'>
```



## 解包

使用频率非常高

1 接收函数返回值

```python
def test():
    return 1, 2, 3

a, b, c = test()	
print(a, b, c)      # 1 2 3


### 赋值语句的左侧不一定非得是3个变量
a, *b = test()
print(a, b)     # 1 [2, 3]
```



2 遍历字典

```python
my_dic = {
    '一': 1,
    '二': 2,
    '三': 3
}

for item in my_dic.items():
    print(item)

# 解包
for key, value in my_dic.items():
    print(key, value)
```



3 传递参数

使用解包技术，可以将元组解包成可变参数，将字典解包成关键字参数 => 这种技术在实践中大量应用

```python
def func(*args):
    print(sum(args))


a = (2, 4, 6)
func(*a)    # 将元组解包成可变参数

def func_2(**kwargs):
    for key, value in kwargs.items():
        print(key, value)

b = {'一': 1, '二': 2}
func_2(**b)     # 将字典解包成关键字参数
```



使用python操作redis时，如果你想一次性向集合中添加多个值，就必须使用解包结束传入参数

- 如果不使用解包技术，就只能在调用sadd方法时手动逐个写入参数，耗时又费力

```python
import redis
from conf.redis_conf import RedisConfig, QueueConfig

r = redis.Redis(host=RedisConfig.host, port=RedisConfig.port,
                password=RedisConfig.password, db=RedisConfig.db)

tup = ('apple', '谷歌', '阿里', '腾讯')

r.sadd('my_set', *tup)


### sadd的方法
def sadd(self, name, *values):
    "Add ``value(s)`` to set ``name``"
    return self.execute_command('SADD', name, *values)
```



4 合并两个字典

```python
dic_1 = {'一': 1}
dic_2 = {'二': 2}

dic_3 = {**dic_1, **dic_2}
print(dic_3)    # {'一': 1, '二': 2}
```







# 生成式

## 列表生成式

灵活快速的生成列表的方式

```python
### 普通方法
lst = []
for i in range(1, 11):
    if i % 2 == 0:
        lst.append(0)
    else:
        lst.append(1)

print(lst)


### 列表生成式
lst = [1 if item % 2 == 1 else 0 for item in range(1, 11)]
print(lst)
```

生成同样内容的列表，列表生成式的方法所使用的代码更少，更加简洁

此外：列表生成式比普通的生成列表的方法更快



@字节码

python不是编译型语言，但还是要被解析成二进制的字节码才能被执行，执行这些字节码的正是python解释器

python中的dis模块，可以查看被编译后的字节码：

- 通过字节码，可以看到普通生成列表的方法和列表生成是生成列表方法之间的根本不同。

```python
import dis

def func1():
    lst = []
    for j in range(1000):
        lst.append(j)


def func2():
    lst = [j for j in range(1000)]

dis.dis(func1)
print('*'*20)
dis.dis(func2)
```

程序执行结果为：

```python
  4           0 BUILD_LIST               0
              2 STORE_FAST               0 (lst)

  5           4 SETUP_LOOP              26 (to 32)
              6 LOAD_GLOBAL              0 (range)
              8 LOAD_CONST               1 (1000)
             10 CALL_FUNCTION            1
             12 GET_ITER
        >>   14 FOR_ITER                14 (to 30)
             16 STORE_FAST               1 (j)

  6          18 LOAD_FAST                0 (lst)
             20 LOAD_ATTR                1 (append)
             22 LOAD_FAST                0 (lst)
             24 CALL_FUNCTION            1
             26 POP_TOP
             28 JUMP_ABSOLUTE           14
        >>   30 POP_BLOCK
        >>   32 LOAD_CONST               0 (None)
             34 RETURN_VALUE
********************
 10           0 LOAD_CONST               1 (<code object <listcomp> at 0x1086dadb0, file "/Users/kwsy/kwsy/coolpython/demo.py", line 10>)
              2 LOAD_CONST               2 ('func2.<locals>.<listcomp>')
              4 MAKE_FUNCTION            0
              6 LOAD_GLOBAL              0 (range)
              8 LOAD_CONST               3 (1000)
             10 CALL_FUNCTION            1
             12 GET_ITER
             14 CALL_FUNCTION            1
             16 STORE_FAST               0 (lst)
             18 LOAD_CONST               0 (None)
             20 RETURN_VALUE      
```

[Link: 官网|字节码解释](https://docs.python.org/3.6/library/dis.html)

对比两段字节码，可以发现，根本的不同在于添加元素的操作。

- func1 中需要执行（20 LOAD_ATTR ）操作，将append方法加载进来，然后执行（CALL_FUNCTION），执行append方法
- func2中添加一个元素时执行的字节码更少，因此速度更快





## 字典生成式

```python
class_dict = {
    'c++': 90,
    'python': 93,
    'java': 95,
    'javascript': 96,
    'node.js': 94
}

new_class_dict = {k: v for k, v in class_dict.items() if v >= 95}	#if筛选key-value对的条件要放到后面
print(new_class_dict)
```





## 集合生成式

```python
lst = [
    {'name': 'python', 'price': 100},
    {'name': 'c++', 'price': 100},
    {'name': 'java', 'price': 100},
    {'name': 'java', 'price': 100},
    {'name': 'python', 'price': 100},
    {'name': 'node', 'price': 100},
]

name_set = {item['name'] for item in lst}
print(name_set)
```